Power_Prediction/__init__.py
Power_Prediction/common_function.py
Power_Prediction/main_power.py
Power_Prediction/make_power.py
Power_Prediction/mssql_auth.py
Power_Prediction/power_predict_15m.py
Power_Prediction/power_predict_hourly.py
Power_Prediction-0.0.1.1.dist-info/METADATA
Power_Prediction-0.0.1.1.dist-info/WHEEL
Power_Prediction-0.0.1.1.dist-info/top_level.txt
Power_Prediction-0.0.1.1.dist-info/RECORD
